src/__init__.py
src/main.py
merge_kicad_sym-0.1.1.dist-info/LICENSE
merge_kicad_sym-0.1.1.dist-info/METADATA
merge_kicad_sym-0.1.1.dist-info/WHEEL
merge_kicad_sym-0.1.1.dist-info/entry_points.txt
merge_kicad_sym-0.1.1.dist-info/top_level.txt
merge_kicad_sym-0.1.1.dist-info/RECORD
