Metadata-Version: 2.1
Name: merge-kicad-sym
Version: 0.1.1
Summary: A script to merge KiCad symbol libraries.
Home-page: https://github.com/McMaster-Rocketry-Team/merge-kicad-sym
Author: Pegasis
Author-email: me@pegasis.site
Classifier: Programming Language :: Python :: 3
Classifier: License :: OSI Approved :: MIT License
Classifier: Operating System :: OS Independent
Requires-Python: >=3.6
License-File: LICENSE
